termsaver-0.7.dist-info/METADATA
termsaver-0.7.dist-info/WHEEL
termsaver-0.7.dist-info/entry_points.txt
termsaver-0.7.dist-info/licenses/LICENSE
termsaver/__init__.py
termsaver/__main__.py
termsaver/data/sw1.txt
termsaver/termsaverlib/__init__.py
termsaver/termsaverlib/common.py
termsaver/termsaverlib/constants.py
termsaver/termsaverlib/exception.py
termsaver/termsaverlib/helper/__init__.py
termsaver/termsaverlib/helper/smartformatter.py
termsaver/termsaverlib/helper/utilities.py
termsaver/termsaverlib/i18n.py
termsaver/termsaverlib/plugins/__init__.py
termsaver/termsaverlib/plugins/exampleplugin/constants.py
termsaver/termsaverlib/plugins/exampleplugin/screen/__init__.py
termsaver/termsaverlib/plugins/exampleplugin/screen/base/__init__.py
termsaver/termsaverlib/plugins/exampleplugin/screen/eps.py
termsaver/termsaverlib/screen/__init__.py
termsaver/termsaverlib/screen/asciiartfarts.py
termsaver/termsaverlib/screen/base/__init__.py
termsaver/termsaverlib/screen/base/filereader.py
termsaver/termsaverlib/screen/base/rssfeed.py
termsaver/termsaverlib/screen/base/urlfetcher.py
termsaver/termsaverlib/screen/clock.py
termsaver/termsaverlib/screen/clocknumber for tremsaver.xlsm
termsaver/termsaverlib/screen/helper/__init__.py
termsaver/termsaverlib/screen/helper/imageconverter.py
termsaver/termsaverlib/screen/helper/position.py
termsaver/termsaverlib/screen/helper/typing.py
termsaver/termsaverlib/screen/helper/urlfetcher.py
termsaver/termsaverlib/screen/helper/xmlreader.py
termsaver/termsaverlib/screen/img2ascii.py
termsaver/termsaverlib/screen/jokes4all.py
termsaver/termsaverlib/screen/matrix.py
termsaver/termsaverlib/screen/programmer.py
termsaver/termsaverlib/screen/quotes4all.py
termsaver/termsaverlib/screen/randtxt.py
termsaver/termsaverlib/screen/rfc.py
termsaver/termsaverlib/screen/rssfeed.py
termsaver/termsaverlib/screen/starwars.py
termsaver/termsaverlib/screen/sysmon.py
termsaver/termsaverlib/screen/urlfetcher.py
termsaver/termsaverlib/screen/wttr.py
termsaver-0.7.dist-info/RECORD
