Metadata-Version: 2.1
Name: termsaver
Version: 0.7
Summary: Simple text-based terminal screensaver.
Keywords: command-line,terminal,screensaver
Author-Email: Bruno Braga <bruno@brunobraga.net>
Maintainer-Email: Eddie Dover <ed@eddiedover.dev>
License: Apache License v2
Project-URL: Homepage, https://www.github.com/brunobraga/termsaver
Project-URL: Bug tracker, https://github.com/brunobraga/termsaver/issues
Requires-Python: >=3.12
Requires-Dist: pillow
Requires-Dist: requests
